qailab/__init__.py
qailab/utils.py
qailab/circuit/__init__.py
qailab/circuit/base.py
qailab/circuit/circuit_builder.py
qailab/circuit/measurement.py
qailab/circuit/utils.py
qailab/circuit/encoding_blocks/__init__.py
qailab/circuit/encoding_blocks/amplitude.py
qailab/circuit/encoding_blocks/rotational.py
qailab/circuit/layer_blocks/__init__.py
qailab/circuit/layer_blocks/entanglers.py
qailab/gradient/__init__.py
qailab/gradient/gradient_calculation.py
qailab/orca_api/__init__.py
qailab/orca_api/networking.py
qailab/orca_api/pt_adapter.py
qailab/qlauncher/__init__.py
qailab/qlauncher/formatter.py
qailab/qlauncher/problem.py
qailab/qlauncher/passes/__init__.py
qailab/qlauncher/passes/backward.py
qailab/qlauncher/passes/forward.py
qailab/torch/__init__.py
qailab/torch/autograd.py
qailab/torch/orca_layer.py
qailab/torch/qlayer.py
qailab/torch/qmodel.py
qailab/torch/layers/__init__.py
qailab/torch/layers/regression.py
qailab-0.1.2.dist-info/licenses/LICENSE
qailab-0.1.2.dist-info/METADATA
qailab-0.1.2.dist-info/WHEEL
qailab-0.1.2.dist-info/top_level.txt
qailab-0.1.2.dist-info/RECORD
