Metadata-Version: 2.4
Name: QAILab
Version: 0.1.2
Summary: Library providing easy to use PyTorch compatible Quantum Neural Network Layers for both universal and photonic quantum computers.
Requires-Python: >=3.11
License-File: LICENSE
Requires-Dist: qiskit<2.0,>=1.4.0
Requires-Dist: qiskit-machine-learning>=0.8.2
Requires-Dist: torch
Requires-Dist: tqdm
Requires-Dist: scikit-learn
Requires-Dist: pandas
Requires-Dist: requests
Requires-Dist: quantum_launcher
Provides-Extra: test
Requires-Dist: pytest; extra == "test"
Requires-Dist: pylint; extra == "test"
Requires-Dist: pre-commit; extra == "test"
Dynamic: license-file
